activities/__init__.py
activities/workflow_pb2.py
activities/workflow_pb2.pyi
activities/workflow_pb2_grpc.py
apis/__init__.py
apis/client_pb2.py
apis/client_pb2.pyi
apis/client_pb2_grpc.py
areas/__init__.py
areas/area_pb2.py
areas/area_pb2.pyi
areas/area_pb2_grpc.py
devices/__init__.py
devices/devices_pb2.py
devices/devices_pb2.pyi
devices/devices_pb2_grpc.py
fatehan_pypb-0.2.0.dist-info/licenses/LICENSE
financial/__init__.py
financial/financial_pb2.py
financial/financial_pb2.pyi
financial/financial_pb2_grpc.py
identities/__init__.py
identities/identities_pb2.py
identities/identities_pb2.pyi
identities/identities_pb2_grpc.py
models/__init__.py
models/fusion_pb2.py
models/fusion_pb2.pyi
models/fusion_pb2_grpc.py
models/models_pb2.py
models/models_pb2.pyi
models/models_pb2_grpc.py
models/operation_pb2.py
models/operation_pb2.pyi
models/operation_pb2_grpc.py
notifies/__init__.py
notifies/notify_pb2.py
notifies/notify_pb2.pyi
notifies/notify_pb2_grpc.py
packets/__init__.py
packets/dataModel_pb2.py
packets/dataModel_pb2.pyi
packets/dataModel_pb2_grpc.py
packets/messages_pb2.py
packets/messages_pb2.pyi
packets/messages_pb2_grpc.py
reports/__init__.py
reports/report_pb2.py
reports/report_pb2.pyi
reports/report_pb2_grpc.py
services/__init__.py
services/api_pb2.py
services/api_pb2.pyi
services/api_pb2_grpc.py
services/repositories_pb2.py
services/repositories_pb2.pyi
services/repositories_pb2_grpc.py
trips/__init__.py
trips/trip_pb2.py
trips/trip_pb2.pyi
trips/trip_pb2_grpc.py
fatehan_pypb-0.2.0.dist-info/METADATA
fatehan_pypb-0.2.0.dist-info/WHEEL
fatehan_pypb-0.2.0.dist-info/top_level.txt
fatehan_pypb-0.2.0.dist-info/RECORD
