Metadata-Version: 2.4
Name: fatehan-pypb
Version: 0.2.0
Summary: gRPC/Protobuf message and service stubs for Fatehan
Author-email: Mehdi Rajabi <96rajabi@gmail.com>
License-Expression: MIT
Project-URL: Repository, https://github.com/FatehanNew/pypb
Classifier: Programming Language :: Python :: 3
Classifier: Operating System :: OS Independent
Classifier: Topic :: Software Development :: Code Generators
Requires-Python: >=3.9
License-File: LICENSE
Requires-Dist: protobuf<7,>=6.31.1
Requires-Dist: grpcio<2,>=1.62
Provides-Extra: dev
Requires-Dist: grpcio-tools>=1.74.0; extra == "dev"
Dynamic: license-file
